openint/__init__.py
openint/_base_client.py
openint/_client.py
openint/_compat.py
openint/_constants.py
openint/_exceptions.py
openint/_files.py
openint/_models.py
openint/_qs.py
openint/_resource.py
openint/_response.py
openint/_streaming.py
openint/_types.py
openint/_version.py
openint/pagination.py
openint/py.typed
openint/_utils/__init__.py
openint/_utils/_logs.py
openint/_utils/_proxy.py
openint/_utils/_reflection.py
openint/_utils/_resources_proxy.py
openint/_utils/_streams.py
openint/_utils/_sync.py
openint/_utils/_transform.py
openint/_utils/_typing.py
openint/_utils/_utils.py
openint/lib/.keep
openint/resources/__init__.py
openint/types/__init__.py
openint/types/check_connection_response.py
openint/types/client_create_connection_params.py
openint/types/client_create_connnector_config_params.py
openint/types/client_create_token_params.py
openint/types/client_get_conector_config_params.py
openint/types/client_get_connection_params.py
openint/types/client_get_message_template_params.py
openint/types/client_list_connection_configs_params.py
openint/types/client_list_connections_params.py
openint/types/client_list_connectors_params.py
openint/types/client_list_connnector_configs_params.py
openint/types/client_list_customers_params.py
openint/types/client_list_events_params.py
openint/types/client_upsert_connnector_config_params.py
openint/types/client_upsert_customer_params.py
openint/types/connector.py
openint/types/create_connection_response.py
openint/types/create_connnector_config_response.py
openint/types/create_token_response.py
openint/types/delete_connection_response.py
openint/types/get_conector_config_response.py
openint/types/get_connection_response.py
openint/types/get_current_user_response.py
openint/types/get_message_template_response.py
openint/types/integration.py
openint/types/list_connection_configs_response.py
openint/types/list_connections_response.py
openint/types/list_connectors_response.py
openint/types/list_connnector_configs_response.py
openint-2.8.0.dist-info/METADATA
openint-2.8.0.dist-info/WHEEL
openint-2.8.0.dist-info/licenses/LICENSE
openint-2.8.0.dist-info/RECORD
